hal/__init__.py
hal/cli.py
hal/config.py
hal/enable_ipywidgets
hal/hal9000.py
hal/sftp.py
hal_cli-0.1.1.dist-info/entry_points.txt
hal_cli-0.1.1.dist-info/WHEEL
hal_cli-0.1.1.dist-info/METADATA
hal_cli-0.1.1.dist-info/RECORD
