Metadata-Version: 2.1
Name: hal-cli
Version: 0.1.1
Summary: HAL manages your machine learning research environment in AWS
Home-page: https://github.com/harrisonpim/hal
License: UNKNOWN
Keywords: machine-learning, aws
Author: Harrison Pim
Author-email: harrison.stroma@gmail.com
Requires-Python: >=3.7
Classifier: License :: OSI Approved :: MIT License
Requires-Dist: paramiko==2.6.0
Requires-Dist: boto3==1.9.198
Requires-Dist: typer==0.2.1
Requires-Dist: wasabi==0.6.0
Requires-Dist: black==19.10b0 ; extra == "dev"
Requires-Dist: flake8==3.8.1 ; extra == "dev"
Requires-Dist: isort==4.3.21 ; extra == "dev"
Requires-Dist: mkdocs-material==5.2.0 ; extra == "doc"
Requires-Dist: typer-cli==0.0.9 ; extra == "doc"
Requires-Dist: pytest==5.4.2 ; extra == "test"
Provides-Extra: dev
Provides-Extra: doc
Provides-Extra: test
